azcam_server/__init__.py
azcam_server/cmdserver.py
azcam_server/database_server.py
azcam_server/favicon.ico
azcam_server/index.html
azcam_server/parameters_server.py
azcam_server/server.py
azcam_server/server_mock.py
azcam_server/shortcuts.py
azcam_server/monitor/__init__.py
azcam_server/monitor/azcammonitor.py
azcam_server/monitor/monitor_processes.py
azcam_server/monitor/monitor_udp.py
azcam_server/monitor/monitor_watchdog.py
azcam_server/monitor/monitorinterface.py
azcam_server/monitor/udpinterface.py
azcam_server/monitor/udpinterface.txt
azcam_server/monitor/webserver/__init__.py
azcam_server/monitor/webserver/index.html
azcam_server/monitor/webserver/monitor_webserver.py
azcam_server/monitor/webserver/parameters_monitor.ini
azcam_server/monitor/webserver/processes.html
azcam_server/monitor/webserver/static/favicon.ico
azcam_server/monitor/webserver/static/monitor.js
azcam_server/monitor/webserver/static/style.css
azcam_server/scripts/__init__.py
azcam_server/scripts/test_arc_controller.py
azcam_server/scripts/test_instrument.py
azcam_server/scripts/test_mag_controller.py
azcam_server/scripts/test_server.py
azcam_server/scripts/test_web.py
azcam_server/tools/__init__.py
azcam_server/tools/controller.py
azcam_server/tools/display.py
azcam_server/tools/ds9display.py
azcam_server/tools/exposure.py
azcam_server/tools/exposure_filename.py
azcam_server/tools/exposure_obstime.py
azcam_server/tools/focus.py
azcam_server/tools/instrument.py
azcam_server/tools/queue.py
azcam_server/tools/sendimage.py
azcam_server/tools/telescope.py
azcam_server/tools/tempcon.py
azcam_server/tools/tempcon_cryocon24.py
azcam_server/tools/arc/__init__.py
azcam_server/tools/arc/camera_server.py
azcam_server/tools/arc/controller_arc.py
azcam_server/tools/arc/exposure_arc.py
azcam_server/tools/arc/receive_data.py
azcam_server/tools/arc/tempcon_arc.py
azcam_server/tools/archon/__init__.py
azcam_server/tools/archon/controller_archon.py
azcam_server/tools/archon/exposure_archon.py
azcam_server-24.2.1.dist-info/LICENSE
azcam_server-24.2.1.dist-info/WHEEL
azcam_server-24.2.1.dist-info/METADATA
azcam_server-24.2.1.dist-info/RECORD
