Metadata-Version: 2.1
Name: azcam-server
Version: 24.2.1
Summary: Server package for AzCam acquisition and analysis package
Keywords: ccd,imaging,astronomy,sensors
Author: Michael Lesser
Author-email: mlesser@arizona.edu
Requires-Python: >= 3.10
Requires-Dist: numpy
Requires-Dist: astropy
Requires-Dist: pywin32; sys_platform == 'win32'
Requires-Dist: psutil
Requires-Dist: fastapi
Requires-Dist: uvicorn
Requires-Dist: jinja2
Requires-Dist: requests
Project-URL: Documentation, https://azcam-server.readthedocs.io/
Project-URL: Repository, https://github.com/mplesser/azcam-server/
